steadiercom/__init__.py
steadiercom/cli.py
steadiercom/steadiercom.py
SteadierCom-0.1.5.dist-info/METADATA
SteadierCom-0.1.5.dist-info/WHEEL
SteadierCom-0.1.5.dist-info/entry_points.txt
SteadierCom-0.1.5.dist-info/top_level.txt
SteadierCom-0.1.5.dist-info/RECORD
