Metadata-Version: 2.1
Name: SteadierCom
Version: 0.1.5
Summary: Microbial community simulation.
Author-email: Daniel Machado <cdanielmachado@gmail.com>
Maintainer-email: Daniel Machado <cdanielmachado@gmail.com>
License: Apache Software License 2.0
Project-URL: homepage, https://github.com/cdanielmachado/steadiercom
Classifier: Development Status :: 4 - Beta
Classifier: Environment :: Console
Classifier: Intended Audience :: Science/Research
Classifier: Topic :: Scientific/Engineering :: Bio-Informatics
Classifier: Programming Language :: Python :: 3.8
Classifier: Programming Language :: Python :: 3.9
Classifier: Programming Language :: Python :: 3.10
Classifier: Programming Language :: Python :: 3.11
Classifier: Programming Language :: Python :: 3.12
Classifier: License :: OSI Approved :: Apache Software License
Requires-Dist: reframed >=1.5.3
Requires-Dist: pandas
Requires-Dist: numpy
Provides-Extra: dev
Requires-Dist: coverage ; extra == 'dev'
Requires-Dist: mypy ; extra == 'dev'
Requires-Dist: pytest ; extra == 'dev'
Requires-Dist: ruff ; extra == 'dev'
